stripe_integrations/__init__.py
stripe_integrations/actions/__init__.py
stripe_integrations/actions/coupons.py
stripe_integrations/actions/customers.py
stripe_integrations/actions/events.py
stripe_integrations/actions/prices.py
stripe_integrations/actions/products.py
stripe_integrations/actions/sources.py
stripe_integrations/actions/subscriptions.py
stripe_integrations/actions/webhooks.py
stripe_integrations/apps.py
stripe_integrations/base/__init__.py
stripe_integrations/base/models.py
stripe_integrations/base/webhooks.py
stripe_integrations/exceptions.py
stripe_integrations/management/__init__.py
stripe_integrations/management/commands/__init__.py
stripe_integrations/management/commands/sync_stripe_coupons.py
stripe_integrations/management/commands/sync_stripe_customers.py
stripe_integrations/management/commands/sync_stripe_prices.py
stripe_integrations/management/commands/sync_stripe_products.py
stripe_integrations/models.py
stripe_integrations/settings.py
stripe_integrations/utils.py
stripe_integrations/webhooks/__init__.py
stripe_integrations/webhooks/base.py
stripe_integrations/webhooks/coupons.py
stripe_integrations/webhooks/customers.py
stripe_integrations/webhooks/prices.py
stripe_integrations/webhooks/products.py
stripe_integrations/webhooks/sources.py
stripe_integrations/webhooks/subscriptions.py
stripe_integrations-0.0.1.dist-info/LICENSE
stripe_integrations-0.0.1.dist-info/METADATA
stripe_integrations-0.0.1.dist-info/WHEEL
stripe_integrations-0.0.1.dist-info/RECORD
