Metadata-Version: 2.1
Name: stripe-integrations
Version: 0.0.1
Summary: Django + Stripe made easy
Home-page: https://twopointone.github.io/stripe-integrations
License: MIT
Keywords: stripe-integrations
Author: Two Point One
Author-email:  oss@twopointone.com 
Maintainer: Vikalp Jain
Maintainer-email: vikalp@twopointone.com
Requires-Python: >=3.9,<4.0
Classifier: Development Status :: 4 - Beta
Classifier: Intended Audience :: Developers
Classifier: License :: OSI Approved :: MIT License
Classifier: Natural Language :: English
Classifier: Operating System :: OS Independent
Classifier: Programming Language :: Python :: 3
Classifier: Programming Language :: Python :: 3.9
Classifier: Programming Language :: Python :: 3.10
Classifier: Programming Language :: Python :: 3.11
Classifier: Programming Language :: Python :: 3.9
Requires-Dist: django (>=3.2.18,<4.0.0)
Requires-Dist: stripe (==5.2.0)
Project-URL: Documentation, https://twopointone.github.io/stripe-integrations
Project-URL: Repository, https://github.com/twopointone/stripe-integrations
